mongoagg/__init__.py
mongoagg/core.py
mongoagg/exceptions.py
mongoagg/models.py
mongoagg-0.1.5.dist-info/LICENSE
mongoagg-0.1.5.dist-info/METADATA
mongoagg-0.1.5.dist-info/WHEEL
mongoagg-0.1.5.dist-info/RECORD
