Metadata-Version: 2.3
Name: mongoagg
Version: 0.1.5
Summary: MongoDB Aggregation Pipeline Builder
Author: scratchingmycranium
Author-email: 41268767+scratchingmycranium@users.noreply.github.com
Requires-Python: >=3.11,<4.0
Classifier: Programming Language :: Python :: 3
Classifier: Programming Language :: Python :: 3.11
Classifier: Programming Language :: Python :: 3.12
Classifier: Programming Language :: Python :: 3.13
Requires-Dist: pydantic (>=2.11.4,<3.0.0)
Requires-Dist: pymongo (>=4.6.2,<5.0.0)
Requires-Dist: pytest (>=8.3.5,<9.0.0)
